{
    "name": "three spheres",
    "camera": {
        "position": [ 13, 2, 3 ],
        "target": [ 0, 0, 0 ],
        "up": [ 0, 1, 0 ],
        "aspect": 0.6,
        "fovy": 20,
        "aperture": 0.1,
        "focus": 10,
        "shutter_open": 0,
        "shutter_close": 0
    },
    "scene": {
        "objects": [
            {
                "name": "floor",
                "type": "sphere",
                "center": [ 0, -1000, 0 ],
                "radius": 1000,
                "velocity": [ 0, 0, 0 ],
                "material": "floor"
            },
            {
                "name": "ball 1",
                "type": "sphere",
                "center": [ 0, 1, 0 ],
                "radius": 1.0,
                "velocity": [ 0, 0, 0 ],
                "material": "ball 1"
            },
            {
                "name": "ball 2",
                "type": "sphere",
                "center": [ -4, 1, 0 ],
                "radius": 1.0,
                "velocity": [ 0, 0, 0 ],
                "material": "ball 2"
            },
            {
                "name": "ball 3",
                "type": "sphere",
                "center": [ 4, 1, 0 ],
                "radius": 1.0,
                "velocity": [ 0, 0, 0 ],
                "material": "ball 3"
            },
            {
                "type": "random",
                "count": 500,
                "bounding box": [ -11, 0.2, -11, 11, 0.2, 11 ],
                "radius range": [0.2, 0.2]
            }
        ],
        "materials": [
            {
                "name": "floor",
                "type": "lambertian",
                "albedo": "checker floor"
            },
            {
                "name": "ball 1",
                "type": "dielectric",
                "basecolor": "white",
                "index_of_refraction": 1.5
            },
            {
                "name": "ball 2",
                "type": "lambertian",
                "albedo": "marble"
            },
            {
                "name": "ball 3",
                "type": "metal",
                "basecolor": "color metal",
                "metallic": 1.0,
                "roughness": 0.0
            }
        ],
        "textures": [
            {
                "name": "checker floor",
                "type": "checker",
                "odd":  "checker color odd",
                "even": "checker color even"
            },
            {
                "name": "checker color odd",
                "type": "solid color",
                "color": [ 0.2, 0.3, 0.1 ]
            },
            {
                "name": "checker color even",
                "type": "solid color",
                "color": [ 0.9, 0.9, 0.9 ]
            },
            {
                "name": "white",
                "type": "solid color",
                "color": [ 1, 1, 1 ]
            },
            {
                "name": "marble",
                "type": "noise",
                "style": 1,
                "scale": 1.0
            },
            {
                "name": "color metal",
                "type": "solid color",
                "color": [ 0.7, 0.6, 0.5 ]
            }
        ]
    }
}